vaex/jupyter/__init__.py
vaex/jupyter/_version.py
vaex/jupyter/bqplot.py
vaex/jupyter/decorators.py
vaex/jupyter/grid.py
vaex/jupyter/ipyleaflet.py
vaex/jupyter/ipympl.py
vaex/jupyter/ipyvolume.py
vaex/jupyter/model.py
vaex/jupyter/traitlets.py
vaex/jupyter/utils.py
vaex/jupyter/view.py
vaex/jupyter/widgets.py
vaex/jupyter/vendor/__init__.py
vaex/jupyter/vendor/contextlib.py
vaex/jupyter/vue/card.vue
vaex/jupyter/vue/column-select.vue
vaex/jupyter/vue/columnlist.vue
vaex/jupyter/vue/link-list.vue
vaex/jupyter/vue/selection.vue
vaex/jupyter/vue/selection_toggle_list.vue
vaex/jupyter/vue/tools-speed-dial.vue
vaex/jupyter/vue/tools-toolbar.vue
vaex/jupyter/vue/vjsf.vue
vaex_jupyter-0.8.2.dist-info/LICENSE.txt
vaex_jupyter-0.8.2.dist-info/METADATA
vaex_jupyter-0.8.2.dist-info/WHEEL
vaex_jupyter-0.8.2.dist-info/entry_points.txt
vaex_jupyter-0.8.2.dist-info/top_level.txt
vaex_jupyter-0.8.2.dist-info/RECORD
