Metadata-Version: 1.0
Name: vaex-jupyter
Version: 0.8.2
Summary: Jupyter notebook and Jupyter lab support for vaex
Home-page: https://www.github.com/maartenbreddels/vaex
Author: Maarten A. Breddels
Author-email: maartenbreddels@gmail.com
License: MIT
Platform: UNKNOWN
